shared_dto_models/__init__.py
autonomize_ai_shared_dto_models-0.0.29.dist-info/METADATA
autonomize_ai_shared_dto_models-0.0.29.dist-info/WHEEL
autonomize_ai_shared_dto_models-0.0.29.dist-info/RECORD
